Metadata-Version: 2.1
Name: rss-reader-palina-yudzina
Version: 4.1
Summary: RSS reader - simple command-line utility.
Home-page: https://github.com/PolinaYud/Final-Task
Author: Polina Yudina
Author-email: polina_yu@list.ru
License: UNKNOWN
Platform: UNKNOWN
Classifier: Programming Language :: Python :: 3.8
Classifier: Operating System :: OS Independent
Requires-Python: >=3.8
